clusterbot/__init__.py
clusterbot/clusterbot.py
clusterbot/progress_bar.py
clusterbot/version.py
slack_clusterbot-1.2.0.dist-info/LICENSE
slack_clusterbot-1.2.0.dist-info/METADATA
slack_clusterbot-1.2.0.dist-info/WHEEL
slack_clusterbot-1.2.0.dist-info/top_level.txt
slack_clusterbot-1.2.0.dist-info/RECORD
